jobsim/__init__.py
jobsim/department.py
jobsim/departments/finance.yaml
jobsim/departments/hr.yaml
jobsim/departments/it.yaml
jobsim/employee.py
jobsim/example.py
jobsim/location.py
jobsim/locations/dubai.yaml
jobsim/locations/krakow.yaml
jobsim/locations/montreal.yaml
jobsim/locations/munich.yaml
jobsim/locations/paris.yaml
jobsim/locations/san_francisco.yaml
jobsim/locations/sydney.yaml
jobsim/trainings_scheduler.py
jobsim-1.5.1.dist-info/LICENSE
jobsim-1.5.1.dist-info/METADATA
jobsim-1.5.1.dist-info/WHEEL
jobsim-1.5.1.dist-info/RECORD
