Metadata-Version: 2.1
Name: jobsim
Version: 1.5.1
Summary: job manager simulator
License: Apache-2.0
Author: Kamil Kania
Author-email: kkania@splunk.com
Requires-Python: >=3.7,<4.0
Classifier: License :: OSI Approved :: Apache Software License
Classifier: Programming Language :: Python :: 3
Classifier: Programming Language :: Python :: 3.7
Classifier: Programming Language :: Python :: 3.8
Classifier: Programming Language :: Python :: 3.9
Classifier: Programming Language :: Python :: 3.10
Classifier: Programming Language :: Python :: 3.11
Requires-Dist: PyYAML (>=6.0,<7.0)
Requires-Dist: dacite (>=1.8.1,<2.0.0)
Requires-Dist: names (>=0.3.0,<0.4.0)
